pants_backend_secrets/__init__.py
pants_backend_secrets/env_secret_provider.py
pants_backend_secrets/exception.py
pants_backend_secrets/goals/decrypt.py
pants_backend_secrets/publish_secret_python.py
pants_backend_secrets/register.py
pants_backend_secrets/secret.py
pants_backend_secrets/secret_request.py
pants_backend_secrets/targets.py
pants_backend_secrets-0.5.0.dist-info/WHEEL
pants_backend_secrets-0.5.0.dist-info/METADATA
pants_backend_secrets-0.5.0.dist-info/licenses/LICENSE-MIT.txt
pants_backend_secrets-0.5.0.dist-info/RECORD
