Metadata-Version: 2.1
Name: pants_backend_secrets
Version: 0.5.0
Summary: A secrets plumbing plugin for the Pants build system
Keywords: pantsbuild,pants,backend,secrets
Author-email: Tom Solberg <me@sbg.dev>
Classifier: Development Status :: 4 - Beta
Classifier: Programming Language :: Python
Classifier: Topic :: Software Development :: Build Tools
Project-URL: Changelog, https://github.com/tgolsson/pants-backends/tree/main/pants-plugins/secrets/CHANGELOG.md
Project-URL: Code, https://github.com/tgolsson/pants-backends/tree/main/pants-plugins/secrets
Project-URL: Repository, https://github.com/tgolsson/pants-backends
